processwrapper/process_wrapper.py
processwrapper/__init__.py
processwrapper/interfaces/process_utility.py
processwrapper/interfaces/process_utility_interface.py
processwrapper/interfaces/__init__.py
process_wrapper-0.3.0.dist-info/DESCRIPTION.rst
process_wrapper-0.3.0.dist-info/METADATA
process_wrapper-0.3.0.dist-info/metadata.json
process_wrapper-0.3.0.dist-info/RECORD
process_wrapper-0.3.0.dist-info/top_level.txt
process_wrapper-0.3.0.dist-info/WHEEL
