Metadata-Version: 2.0
Name: process-wrapper
Version: 0.3.0
Summary: Context manager for background command-line programs
Home-page: https://github.com/marc-lopez/process-wrapper
Author: Marc Lopez
Author-email: marc.rainier.lopez@gmail.com
License: LICENSE.txt
Platform: linux2
Platform: win32
Classifier: Development Status :: 3 - Alpha
Classifier: Environment :: Console
Classifier: Intended Audience :: Developers
Classifier: Intended Audience :: System Administrators
Classifier: License :: OSI Approved :: MIT License
Classifier: Programming Language :: Python
Classifier: Topic :: Software Development :: Libraries :: Python Modules
Requires-Dist: psutil (>=2.2.1)
